norfetools.py
norfetools-0.0.1.dist-info/METADATA
norfetools-0.0.1.dist-info/WHEEL
norfetools-0.0.1.dist-info/top_level.txt
norfetools-0.0.1.dist-info/RECORD
